tri_struct/__init__.py
tri_struct/_cstruct.cpython-38-darwin.so
tri_struct/_pystruct.py
tri.struct-4.1.0.dist-info/AUTHORS.rst
tri.struct-4.1.0.dist-info/LICENSE
tri.struct-4.1.0.dist-info/METADATA
tri.struct-4.1.0.dist-info/WHEEL
tri.struct-4.1.0.dist-info/top_level.txt
tri.struct-4.1.0.dist-info/RECORD
