Metadata-Version: 2.1
Name: tri.struct
Version: 4.1.0
Summary: tri.struct supplies classes that can be used like dictionaries and as objects with attribute access at the same time
Home-page: https://github.com/TriOptima/tri.struct
Author: Johan Lübcke
Author-email: johan.lubcke@trioptima.com
License: BSD
Keywords: tri.struct
Platform: UNKNOWN
Classifier: Development Status :: 5 - Production/Stable
Classifier: Intended Audience :: Developers
Classifier: License :: OSI Approved :: BSD License
Classifier: Natural Language :: English
Classifier: Programming Language :: Python :: 2
Classifier: Programming Language :: Python :: 2.7
Classifier: Programming Language :: Python :: 3
Classifier: Programming Language :: Python :: 3.6
